bashbox/__init__.py
bashbox/__main__.py
bashbox/bashbox.py
bashbox-2.2.0.dist-info/LICENSE
bashbox-2.2.0.dist-info/METADATA
bashbox-2.2.0.dist-info/WHEEL
bashbox-2.2.0.dist-info/top_level.txt
bashbox-2.2.0.dist-info/RECORD
