Metadata-Version: 2.1
Name: bashbox
Version: 2.2.0
Summary: Textboxes for Python
Author-email: Bash Elliott <rackodo.business@gmail.com>
Project-URL: Homepage, https://github.com/rackodo/bashbox
Project-URL: Bug Tracker, https://github.com/rackodo/bashbox/issues
Classifier: Programming Language :: Python :: 3
Classifier: License :: OSI Approved :: MIT License
Classifier: Operating System :: OS Independent
Requires-Python: >=3.7
License-File: LICENSE
